folder_structure_generator_7edge/__init__.py
folder_structure_generator_7edge/generator.py
folder_structure_generator_7edge_test1-1.0.0.dist-info/METADATA
folder_structure_generator_7edge_test1-1.0.0.dist-info/WHEEL
folder_structure_generator_7edge_test1-1.0.0.dist-info/entry_points.txt
folder_structure_generator_7edge_test1-1.0.0.dist-info/top_level.txt
folder_structure_generator_7edge_test1-1.0.0.dist-info/RECORD
